x7/__init__.py
x7/shell.py
x7/lib/__init__.py
x7/lib/__version__.py
x7/lib/annotations.py
x7/lib/bidict.py
x7/lib/capture.py
x7/lib/inspect_more.py
x7/lib/iters.py
x7/lib/patch.py
x7/lib/shell_tools.py
x7/lib/shell_tools_load.py
x7/lib/subclasses.py
x7/lib/timer.py
x7/lib/utils/__init__.py
x7/lib/utils/dev_update.py
x7_lib-0.6.2.dist-info/LICENSE
x7_lib-0.6.2.dist-info/METADATA
x7_lib-0.6.2.dist-info/WHEEL
x7_lib-0.6.2.dist-info/top_level.txt
x7_lib-0.6.2.dist-info/RECORD
